rtl/apb_slave.sv
module apb_slave (
    input  logic        PCLK,
    input  logic        PRESETn,
    input  logic        PSEL,
    input  logic        PENABLE,
    input  logic        PWRITE,
    input  logic [7:0]  PADDR,
    input  logic [31:0] PWDATA,
    output logic [31:0] PRDATA,
    output logic        PREADY,
    output logic        PSLVERR
);

    // Register addresses. Only the low byte of PADDR is used in this lab.
    localparam logic [7:0] CTRL_ADDR   = 8'h00;
    localparam logic [7:0] STATUS_ADDR = 8'h04;
    localparam logic [7:0] DATA_ADDR   = 8'h08;

    // STATUS is read-only and returns the same value every time.
    localparam logic [31:0] STATUS_VALUE = 32'h0000_00A5;

    logic [31:0] ctrl_reg;
    logic [31:0] data_reg;

    logic        apb_access;
    logic        wait_done;
    logic        transfer_done;
    logic        valid_addr;

    // The APB access phase is when both PSEL and PENABLE are high.
    assign apb_access = PSEL && PENABLE;

    // PREADY is low for the first access cycle, then high on the next cycle.
    // This shows how an APB slave can add a simple wait state.
    assign PREADY = apb_access && wait_done;

    // A transfer finishes only when the slave says it is ready.
    assign transfer_done = apb_access && PREADY;

    // Check whether the address matches one of the registers.
    always_comb begin
        case (PADDR)
            CTRL_ADDR,
            STATUS_ADDR,
            DATA_ADDR:   valid_addr = 1'b1;
            default:     valid_addr = 1'b0;
        endcase
    end

    // wait_done remembers that the first access cycle has already passed.
    always_ff @(posedge PCLK) begin
        if (!PRESETn) begin
            wait_done <= 1'b0;
        end else if (apb_access && !wait_done) begin
            wait_done <= 1'b1;
        end else begin
            wait_done <= 1'b0;
        end
    end

    // PSLVERR is reported when an APB transfer completes with an invalid address.
    assign PSLVERR = transfer_done && !valid_addr;

    // Write registers on the clock edge during an APB write access.
    // Reset is synchronous and active-low, so it is checked inside the clocked block.
    always_ff @(posedge PCLK) begin
        if (!PRESETn) begin
            ctrl_reg <= 32'h0000_0000;
            data_reg <= 32'h0000_0000;
        end else if (transfer_done && PWRITE) begin
            case (PADDR)
                CTRL_ADDR: ctrl_reg <= PWDATA;
                DATA_ADDR: data_reg <= PWDATA;
                default: begin
                    // STATUS is read-only and invalid addresses do not change registers.
                end
            endcase
        end
    end

    // Return read data when an APB read transfer completes.
    // For write cycles or idle/setup cycles, PRDATA is driven to zero.
    always_comb begin
        PRDATA = 32'h0000_0000;

        if (transfer_done && !PWRITE) begin
            case (PADDR)
                CTRL_ADDR:   PRDATA = ctrl_reg;
                STATUS_ADDR: PRDATA = STATUS_VALUE;
                DATA_ADDR:   PRDATA = data_reg;
                default:     PRDATA = 32'h0000_0000;
            endcase
        end
    end

endmodule

tb/tb_apb_slave.sv
`timescale 1ns/1ps

module tb_apb_slave;

    localparam logic [7:0] CTRL_ADDR    = 8'h00;
    localparam logic [7:0] STATUS_ADDR  = 8'h04;
    localparam logic [7:0] DATA_ADDR    = 8'h08;
    localparam logic [7:0] INVALID_ADDR = 8'h0C;

    localparam logic [31:0] STATUS_VALUE = 32'h0000_00A5;

    logic        PCLK;
    logic        PRESETn;
    logic        PSEL;
    logic        PENABLE;
    logic        PWRITE;
    logic [7:0]  PADDR;
    logic [31:0] PWDATA;
    logic [31:0] PRDATA;
    logic        PREADY;
    logic        PSLVERR;

    int error_count;

    apb_slave dut (
        .PCLK    (PCLK),
        .PRESETn (PRESETn),
        .PSEL    (PSEL),
        .PENABLE (PENABLE),
        .PWRITE  (PWRITE),
        .PADDR   (PADDR),
        .PWDATA  (PWDATA),
        .PRDATA  (PRDATA),
        .PREADY  (PREADY),
        .PSLVERR (PSLVERR)
    );

    // 100 MHz clock: 10 ns period.
    initial begin
        PCLK = 1'b0;
        forever #5 PCLK = ~PCLK;
    end

    // Simple checker. Each mismatch increments error_count.
    task automatic check_equal(
        input string name,
        input logic [31:0] actual,
        input logic [31:0] expected
    );
        begin
            if (actual !== expected) begin
                $display("ERROR: %s expected 0x%08h, got 0x%08h",
                         name, expected, actual);
                error_count++;
            end
        end
    endtask

    // APB write transfer:
    // 1. setup phase: PSEL=1, PENABLE=0
    // 2. access phase: PSEL=1, PENABLE=1
    // 3. wait until PREADY=1, then the transfer is complete
    task automatic apb_write(
        input logic [7:0]  addr,
        input logic [31:0] data
    );
        begin
            @(posedge PCLK);
            PSEL    <= 1'b1;
            PENABLE <= 1'b0;
            PWRITE  <= 1'b1;
            PADDR   <= addr;
            PWDATA  <= data;

            @(posedge PCLK);
            PENABLE <= 1'b1;

            do begin
                @(posedge PCLK);
                #1;
            end while (!PREADY);

            @(posedge PCLK);
            #1;
            PSEL    <= 1'b0;
            PENABLE <= 1'b0;
            PWRITE  <= 1'b0;
            PADDR   <= 8'h00;
            PWDATA  <= 32'h0000_0000;
        end
    endtask

    // APB read transfer. Data and PSLVERR are sampled when PREADY is high.
    task automatic apb_read(
        input  logic [7:0]  addr,
        output logic [31:0] data,
        output logic        error
    );
        begin
            @(posedge PCLK);
            PSEL    <= 1'b1;
            PENABLE <= 1'b0;
            PWRITE  <= 1'b0;
            PADDR   <= addr;
            PWDATA  <= 32'h0000_0000;

            @(posedge PCLK);
            PENABLE <= 1'b1;

            do begin
                @(posedge PCLK);
                #1;
            end while (!PREADY);

            data  = PRDATA;
            error = PSLVERR;

            @(posedge PCLK);
            #1;
            PSEL    <= 1'b0;
            PENABLE <= 1'b0;
            PADDR   <= 8'h00;
        end
    endtask

    initial begin
        logic [31:0] read_data;
        logic        read_error;

        $dumpfile("wave.vcd");
        $dumpvars(0, tb_apb_slave);

        error_count = 0;

        PSEL    = 1'b0;
        PENABLE = 1'b0;
        PWRITE  = 1'b0;
        PADDR   = 8'h00;
        PWDATA  = 32'h0000_0000;
        PRESETn = 1'b0;

        // Synchronous active-low reset: hold reset low across clock edges.
        repeat (3) @(posedge PCLK);
        PRESETn <= 1'b1;
        @(posedge PCLK);

        // Reset should clear the RW registers.
        apb_read(CTRL_ADDR, read_data, read_error);
        check_equal("CTRL reset value", read_data, 32'h0000_0000);
        check_equal("CTRL reset PSLVERR", {31'b0, read_error}, 32'h0000_0000);

        apb_read(DATA_ADDR, read_data, read_error);
        check_equal("DATA reset value", read_data, 32'h0000_0000);
        check_equal("DATA reset PSLVERR", {31'b0, read_error}, 32'h0000_0000);

        // CTRL register write/read test.
        apb_write(CTRL_ADDR, 32'h1234_5678);
        apb_read(CTRL_ADDR, read_data, read_error);
        check_equal("CTRL readback", read_data, 32'h1234_5678);
        check_equal("CTRL readback PSLVERR", {31'b0, read_error}, 32'h0000_0000);

        // DATA register write/read test.
        apb_write(DATA_ADDR, 32'hCAFE_BABE);
        apb_read(DATA_ADDR, read_data, read_error);
        check_equal("DATA readback", read_data, 32'hCAFE_BABE);
        check_equal("DATA readback PSLVERR", {31'b0, read_error}, 32'h0000_0000);

        // STATUS is read-only and always returns the fixed value.
        apb_write(STATUS_ADDR, 32'hFFFF_FFFF);
        apb_read(STATUS_ADDR, read_data, read_error);
        check_equal("STATUS fixed value", read_data, STATUS_VALUE);
        check_equal("STATUS read PSLVERR", {31'b0, read_error}, 32'h0000_0000);

        // Invalid address should assert PSLVERR during the access phase.
        apb_read(INVALID_ADDR, read_data, read_error);
        check_equal("Invalid address PSLVERR", {31'b0, read_error}, 32'h0000_0001);

        if (error_count == 0) begin
            $display("PASS");
        end else begin
            $display("FAIL");
        end

        $finish;
    end

endmodule

wave.vcd
$date
	Tue May 12 21:55:31 2026
$end
$version
	Icarus Verilog
$end
$timescale
	1ps
$end
$scope module tb_apb_slave $end
$var wire 1 ! PSLVERR $end
$var wire 1 " PREADY $end
$var wire 32 # PRDATA [31:0] $end
$var parameter 8 $ CTRL_ADDR $end
$var parameter 8 % DATA_ADDR $end
$var parameter 8 & INVALID_ADDR $end
$var parameter 8 ' STATUS_ADDR $end
$var parameter 32 ( STATUS_VALUE $end
$var reg 8 ) PADDR [7:0] $end
$var reg 1 * PCLK $end
$var reg 1 + PENABLE $end
$var reg 1 , PRESETn $end
$var reg 1 - PSEL $end
$var reg 32 . PWDATA [31:0] $end
$var reg 1 / PWRITE $end
$var integer 32 0 error_count [31:0] $end
$scope module dut $end
$var wire 8 1 PADDR [7:0] $end
$var wire 1 * PCLK $end
$var wire 1 + PENABLE $end
$var wire 1 " PREADY $end
$var wire 1 , PRESETn $end
$var wire 1 - PSEL $end
$var wire 1 ! PSLVERR $end
$var wire 32 2 PWDATA [31:0] $end
$var wire 1 / PWRITE $end
$var wire 1 3 apb_access $end
$var wire 1 4 transfer_done $end
$var parameter 8 5 CTRL_ADDR $end
$var parameter 8 6 DATA_ADDR $end
$var parameter 8 7 STATUS_ADDR $end
$var parameter 32 8 STATUS_VALUE $end
$var reg 32 9 PRDATA [31:0] $end
$var reg 32 : ctrl_reg [31:0] $end
$var reg 32 ; data_reg [31:0] $end
$var reg 1 < valid_addr $end
$var reg 1 = wait_done $end
$upscope $end
$scope begin $unm_blk_19 $end
$var reg 32 > read_data [31:0] $end
$var reg 1 ? read_error $end
$upscope $end
$scope task apb_read $end
$upscope $end
$scope task apb_write $end
$upscope $end
$scope task check_equal $end
$upscope $end
$upscope $end
$enddefinitions $end
$comment Show the parameter values. $end
$dumpall
b10100101 8
b100 7
b1000 6
b0 5
b10100101 (
b100 '
b1100 &
b1000 %
b0 $
$end
#0
$dumpvars
x?
bx >
x=
1<
bx ;
bx :
b0 9
04
03
b0 2
b0 1
b0 0
0/
b0 .
0-
0,
0+
0*
b0 )
b0 #
0"
0!
$end
#5000
0=
b0 ;
b0 :
1*
#10000
0*
#15000
1*
#20000
0*
#25000
1,
1*
#30000
0*
#35000
1*
#40000
0*
#45000
1-
1*
#50000
0*
#55000
13
1+
1*
#60000
0*
#65000
14
1"
1=
1*
#70000
0*
#75000
04
0"
0=
1*
#76000
03
0+
0-
0?
b0 >
#80000
0*
#85000
b1000 )
b1000 1
1-
1*
#90000
0*
#95000
13
1+
1*
#100000
0*
#105000
14
1"
1=
1*
#110000
0*
#115000
04
0"
0=
1*
#116000
03
b0 )
b0 1
0+
0-
#120000
0*
#125000
b10010001101000101011001111000 .
b10010001101000101011001111000 2
1/
1-
1*
#130000
0*
#135000
13
1+
1*
#140000
0*
#145000
14
1"
1=
1*
#150000
0*
#155000
04
0"
b10010001101000101011001111000 :
0=
1*
#156000
03
b0 .
b0 2
0/
0+
0-
#160000
0*
#165000
1-
1*
#170000
0*
#175000
13
1+
1*
#180000
0*
#185000
b10010001101000101011001111000 #
b10010001101000101011001111000 9
14
1"
1=
1*
#190000
0*
#195000
b0 #
b0 9
04
0"
0=
1*
#196000
03
0+
0-
b10010001101000101011001111000 >
#200000
0*
#205000
b11001010111111101011101010111110 .
b11001010111111101011101010111110 2
b1000 )
b1000 1
1/
1-
1*
#210000
0*
#215000
13
1+
1*
#220000
0*
#225000
14
1"
1=
1*
#230000
0*
#235000
04
0"
b11001010111111101011101010111110 ;
0=
1*
#236000
03
b0 .
b0 2
b0 )
b0 1
0/
0+
0-
#240000
0*
#245000
b1000 )
b1000 1
1-
1*
#250000
0*
#255000
13
1+
1*
#260000
0*
#265000
b11001010111111101011101010111110 #
b11001010111111101011101010111110 9
14
1"
1=
1*
#270000
0*
#275000
b0 #
b0 9
04
0"
0=
1*
#276000
03
b0 )
b0 1
0+
0-
b11001010111111101011101010111110 >
#280000
0*
#285000
b11111111111111111111111111111111 .
b11111111111111111111111111111111 2
b100 )
b100 1
1/
1-
1*
#290000
0*
#295000
13
1+
1*
#300000
0*
#305000
14
1"
1=
1*
#310000
0*
#315000
04
0"
0=
1*
#316000
03
b0 .
b0 2
b0 )
b0 1
0/
0+
0-
#320000
0*
#325000
b100 )
b100 1
1-
1*
#330000
0*
#335000
13
1+
1*
#340000
0*
#345000
b10100101 #
b10100101 9
14
1"
1=
1*
#350000
0*
#355000
b0 #
b0 9
04
0"
0=
1*
#356000
03
b0 )
b0 1
0+
0-
b10100101 >
#360000
0*
#365000
0<
b1100 )
b1100 1
1-
1*
#370000
0*
#375000
13
1+
1*
#380000
0*
#385000
1!
14
1"
1=
1*
#390000
0*
#395000
0!
04
0"
0=
1*
#396000
1<
03
b0 )
b0 1
0+
0-
1?
b0 >
